pygenomeviz/__init__.py
pygenomeviz/const.py
pygenomeviz/exception.py
pygenomeviz/genomeviz.py
pygenomeviz/logger.py
pygenomeviz/patches.py
pygenomeviz/typing.py
pygenomeviz/align/__init__.py
pygenomeviz/align/coord.py
pygenomeviz/align/tool/__init__.py
pygenomeviz/align/tool/base.py
pygenomeviz/align/tool/blast.py
pygenomeviz/align/tool/last.py
pygenomeviz/align/tool/mmseqs.py
pygenomeviz/align/tool/mummer.py
pygenomeviz/align/tool/pmauve.py
pygenomeviz/gui/__init__.py
pygenomeviz/gui/app.py
pygenomeviz/gui/config.py
pygenomeviz/gui/plot.py
pygenomeviz/gui/utils.py
pygenomeviz/gui/assets/pgv_demo.gif
pygenomeviz/parser/__init__.py
pygenomeviz/parser/fasta.py
pygenomeviz/parser/genbank.py
pygenomeviz/parser/gff.py
pygenomeviz/scripts/__init__.py
pygenomeviz/scripts/blast.py
pygenomeviz/scripts/download.py
pygenomeviz/scripts/gui.py
pygenomeviz/scripts/mmseqs.py
pygenomeviz/scripts/mummer.py
pygenomeviz/scripts/pmauve.py
pygenomeviz/segment/__init__.py
pygenomeviz/segment/feature.py
pygenomeviz/track/__init__.py
pygenomeviz/track/base.py
pygenomeviz/track/feature.py
pygenomeviz/track/link.py
pygenomeviz/utils/__init__.py
pygenomeviz/utils/download.py
pygenomeviz/utils/helper.py
pygenomeviz/utils/plot.py
pygenomeviz/viewer/__init__.py
pygenomeviz/viewer/pgv-viewer-template.html
pygenomeviz/viewer/assets/pgv-viewer.js
pygenomeviz/viewer/assets/lib/jquery.min.js
pygenomeviz/viewer/assets/lib/micromodal.css
pygenomeviz/viewer/assets/lib/micromodal.min.js
pygenomeviz/viewer/assets/lib/panzoom.min.js
pygenomeviz/viewer/assets/lib/popper.min.js
pygenomeviz/viewer/assets/lib/spectrum.min.css
pygenomeviz/viewer/assets/lib/spectrum.min.js
pygenomeviz/viewer/assets/lib/tabulator.min.css
pygenomeviz/viewer/assets/lib/tabulator.min.js
pygenomeviz/viewer/assets/lib/tippy-bundle.umd.min.js
pygenomeviz/viewer/assets/lib/LICENSE/LICENSE.jquery
pygenomeviz/viewer/assets/lib/LICENSE/LICENSE.micromodal
pygenomeviz/viewer/assets/lib/LICENSE/LICENSE.panzoom
pygenomeviz-1.6.1.dist-info/METADATA
pygenomeviz-1.6.1.dist-info/WHEEL
pygenomeviz-1.6.1.dist-info/entry_points.txt
pygenomeviz-1.6.1.dist-info/licenses/LICENSE
pygenomeviz-1.6.1.dist-info/RECORD
