Metadata-Version: 2.3
Name: pygenomeviz
Version: 1.6.1
Summary: A genome visualization python package for comparative genomics
Project-URL: homepage, https://moshi4.github.io/pyGenomeViz/
Project-URL: repository, https://github.com/moshi4/pyGenomeViz/
Author: moshi4
License: MIT
Keywords: bioinformatics,comparative-genomics,genomics,matplotlib,visualization
Classifier: Framework :: Matplotlib
Classifier: Intended Audience :: Science/Research
Classifier: Topic :: Scientific/Engineering :: Bio-Informatics
Requires-Python: >=3.9
Requires-Dist: biopython>=1.80
Requires-Dist: matplotlib>=3.6.3
Requires-Dist: numpy>=1.21
Provides-Extra: gui
Requires-Dist: streamlit>=1.45.0; extra == 'gui'
